bmmflux/__init__.py
bmmflux/read_bmmflux.py
btmm_process/__init__.py
btmm_process/calibrate.py
btmm_process/driver.py
btmm_process/dts_plots.py
btmm_process/dtsarch.py
btmm_process/flyfox.py
btmm_process/labeler.py
btmm_process/readDTS.py
btmm_process/wind_speed.py
btmm_process/xr_helper.py
pyfocs/__init__.py
pyfocs/align.py
pyfocs/calibrate.py
pyfocs/check.py
pyfocs/data.py
pyfocs/dts_plots.py
pyfocs/dtsarch.py
pyfocs/flyfox.py
pyfocs/labeler.py
pyfocs/readDTS.py
pyfocs/stats.py
pyfocs/wind_speed.py
pyfocs/xr_helper.py
pyfocs-0.5.1.data/scripts/PyFOX.py
pyfocs-0.5.1.dist-info/LICENSE
pyfocs-0.5.1.dist-info/METADATA
pyfocs-0.5.1.dist-info/WHEEL
pyfocs-0.5.1.dist-info/top_level.txt
pyfocs-0.5.1.dist-info/RECORD
