Metadata-Version: 2.1
Name: pyfocs
Version: 0.5.1
Summary: Processing of meteorological FODS data.
Home-page: https://github.com/klapo/pyfocs
Author: Karl Lapo and Anita Freundorfer
Author-email: karl.lapo@uni-bayreuth.de
License: GNU General Public License, version 3 (GPLv3)
Project-URL: Changelog, https://github.com/klapo/pyfocs/blob/master/CHANGELOG.rst
Project-URL: Issue Tracker, https://github.com/klapo/pyfocs/issues
Platform: UNKNOWN
Classifier: Development Status :: 3 - Alpha
Classifier: Intended Audience :: Developers
Classifier: License :: OSI Approved :: MIT License
Classifier: Operating System :: Unix
Classifier: Operating System :: POSIX
Classifier: Operating System :: Microsoft :: Windows
Classifier: Programming Language :: Python
Classifier: Programming Language :: Python :: 3.6
Classifier: Programming Language :: Python :: 3.7
Classifier: Programming Language :: Python :: 3.8
Classifier: Programming Language :: Python :: Implementation :: CPython
Classifier: Programming Language :: Python :: Implementation :: PyPy
Classifier: Topic :: Utilities
Requires-Python: >=3.6
Requires-Dist: numpy
Requires-Dist: pandas
Requires-Dist: scipy
Requires-Dist: netcdf4
Requires-Dist: xarray (>=0.15)
Requires-Dist: xmltodict
Requires-Dist: pyyaml (>=5.1)
Requires-Dist: matplotlib (>3)
Requires-Dist: dtscalibration
